prueba_test_cam/data_catcher.v
module data_catcher (
	input [7:0] data,
	input href, 				
	input pclk,
	input vsync,
	
	output reg [14:0] DP_RAM_addr_out = 0,
	output reg [7:0] DP_RAM_data_out,
	output reg DP_RAM_regW //autoriza escritura en la dpram
);

	reg [1:0] FSM_state = 0; //dos estados: WAIT_FRAME_START & ROW_CAPTURE
    reg pixel_half = 0; //indica si va almacenado medio pixel (1 Byte) o uno completo
	reg [15:0] temp_rgb; //registro temporal para guardar pixel completo, asumiendo RGB565
	
	localparam MAX_MEMORY = 2 ** 15; //tamaño total de la dpram
	localparam WAIT_FRAME_START = 0;
	localparam ROW_CAPTURE = 1;
	
	
	always @(posedge pclk)
	begin 
	
	case(FSM_state)
	
	WAIT_FRAME_START: begin //wait for VSYNC
	   FSM_state <= (!vsync) ? ROW_CAPTURE : WAIT_FRAME_START;
	   pixel_half <= 0;
	end
	
	ROW_CAPTURE: begin 
	   	FSM_state <= vsync ? WAIT_FRAME_START : ROW_CAPTURE; 
		if (href) begin
		pixel_half <= ~ pixel_half;
		
			if (pixel_half == 0) begin
				temp_rgb [15:8] = data;
				DP_RAM_regW <= 0;
			end else begin
				DP_RAM_addr_out <= DP_RAM_addr_out + 1;
				temp_rgb [7:0] = data;
				DP_RAM_data_out = {temp_rgb[15:13], temp_rgb[10:8],temp_rgb[4:3]}; //RGB565 a RGB332
				DP_RAM_regW <= 1;
				
			end

	   	end
	end
	
	endcase

	if (DP_RAM_addr_out == MAX_MEMORY - 1) begin
			DP_RAM_addr_out <= 0;
		end

	end
	
endmodule

/*****************************************************************
	OBJETIVO DE ESTE MÓDULO:
	-Transformar los datos de entrada de RGB565 a RGB332
	-Enviar los datos transformados a la dpram
	---> este módulo solo interactua entre la cámara y la dpram <---

	**Cada ciclo del reloj pclk se envía un byte (es el mismo xclk)
	**El reloj href se pone en ALTO durante el envío de la fila (640x2 pclk)
	**hsync mantiene una señal con frecuencia estable dentro de la cual está 
	cada fila, de forma que se puedan sincronizar
	**vsync se pone en alto al inicio del frame y al final del frame

******************************************************************/

camera_catcher_TB/data_catcher_TB.v
module data_catcher_TB;

	//inputs
	reg [7:0] data;
	reg href; 				
	reg pclk;
	reg vsync;
	//outputs
	wire [14:0] DP_RAM_addr_out; 
	wire [7:0] DP_RAM_data_out;
	wire DP_RAM_regW;


	data_catcher dc (
	.data(data),
	.href(href),
	.pclk(pclk),
	.vsync(vsync),
	.DP_RAM_addr_out(DP_RAM_addr_out),
	.DP_RAM_data_out(DP_RAM_data_out),
	.DP_RAM_regW(DP_RAM_regW)
	);
	
	initial begin
	//DP_RAM_addr_out = 0;
	pclk = 0;
	vsync = 0;
	href = 0;
	data = 0;
	#5;
	#50;

	vsync = 1;
	#10;
	vsync = 0;
	#10;
	href = 1; 
	data = 8'b11011011;
	#10; 
	data = 8'b01101101;
	#10;
	data = 8'b00100001; //1
	#10;
	data = 8'b00001000;
	#10;
	data = 8'b01000010; //2
	#10;
	data = 8'b00010000;
	#10;
	data = 8'b01100011; //3
	#10;
	data = 8'b00011000;
	#10;
	data = 8'b10000100; //4
	#10;
	data = 8'b00000000;
	#10;
	data = 8'b10100101; //5
	#10;
	data = 8'b00001000;
	#10;
	href = 0;
	#10;
	vsync = 0;
	end
	
	always pclk = #5 ~pclk;

	initial begin: TEST_CASE
	$dumpfile("data_catcher_TB.vcd");
	$dumpvars(-1, dc);
	#1000000 $finish;
	end	

endmodule

camera_catcher_TB/simulation/data_catcher_TB.vcd
$date
	Sun Nov 10 13:55:25 2019
$end
$version
	Icarus Verilog
$end
$timescale
	1s
$end
$scope module data_catcher_TB $end
$scope module dc $end
$var wire 8 ! data [7:0] $end
$var wire 1 " href $end
$var wire 1 # pclk $end
$var wire 1 $ vsync $end
$var reg 15 % DP_RAM_addr_out [14:0] $end
$var reg 8 & DP_RAM_data_out [7:0] $end
$var reg 1 ' DP_RAM_regW $end
$var reg 2 ( FSM_state [1:0] $end
$var reg 1 ) pixel_half $end
$var reg 16 * temp_rgb [15:0] $end
$upscope $end
$upscope $end
$enddefinitions $end
#0
$dumpvars
bx *
0)
b0 (
x'
bx &
b0 %
0$
0#
0"
b0 !
$end
#5
b1 (
1#
#10
0#
#15
1#
#20
0#
#25
1#
#30
0#
#35
1#
#40
0#
#45
1#
#50
0#
#55
b0 (
1#
1$
#60
0#
#65
b1 (
1#
0$
#70
0#
#75
0'
1)
b11011011xxxxxxxx *
1#
b11011011 !
1"
#80
0#
#85
1'
b1 %
0)
b11001101 &
b1101101101101101 *
1#
b1101101 !
#90
0#
#95
0'
1)
b10000101101101 *
1#
b100001 !
#100
0#
#105
1'
b10 %
0)
b100101 &
b10000100001000 *
1#
b1000 !
#110
0#
#115
0'
1)
b100001000001000 *
1#
b1000010 !
#120
0#
#125
1'
b11 %
0)
b1001010 &
b100001000010000 *
1#
b10000 !
#130
0#
#135
0'
1)
b110001100010000 *
1#
b1100011 !
#140
0#
#145
1'
b100 %
0)
b1101111 &
b110001100011000 *
1#
b11000 !
#150
0#
#155
0'
1)
b1000010000011000 *
1#
b10000100 !
#160
0#
#165
1'
b101 %
0)
b10010000 &
b1000010000000000 *
1#
b0 !
#170
0#
#175
0'
1)
b1010010100000000 *
1#
b10100101 !
#180
0#
#185
1'
b110 %
0)
b10110101 &
b1010010100001000 *
1#
b1000 !
#190
0#
#195
1#
0"
